setup.cfg
setup.py
mailerlite/__init__.py
mailerlite/api.py
mailerlite/campaign.py
mailerlite/subscriber.py
mailerlite/subscriber_list.py
python_mailerlite.egg-info/PKG-INFO
python_mailerlite.egg-info/SOURCES.txt
python_mailerlite.egg-info/dependency_links.txt
python_mailerlite.egg-info/requires.txt
python_mailerlite.egg-info/top_level.txt