Metadata-Version: 1.1
Name: python-mailerlite
Version: 0.1b0
Summary: A Python wrapper around the MailerLite API
Home-page: https://github.com/LarryBrid/python-mailerlite
Author: Cam Fulton
Author-email: jcameronfulton@gmail.com
License: MIT
Download-URL: https://github.com/LarryBrid/python-mailerlite/tarball/0.1
Keywords: mailerlite,api,python-mailerlite
Platform: UNKNOWN
Classifier: Development Status :: 4 - Beta
Classifier: Intended Audience :: Developers
Classifier: License :: OSI Approved :: MIT License
Classifier: Operating System :: OS Independent
Classifier: Topic :: Software Development :: Libraries :: Python Modules
Classifier: Topic :: Communications :: Email
Classifier: Topic :: Internet
Classifier: Programming Language :: Python
Classifier: Programming Language :: Python :: 2
Classifier: Programming Language :: Python :: 2.7
